{
  "market": "dax40",
  "scanned_at": "2026-03-06T18:26:39.617405",
  "min_yield": 5.0,
  "total_candidates": 4,
  "candidates": [
    {
      "ticker": "VOW3.DE",
      "name": "VOLKSWAGEN AG                 V",
      "asset_type": "stock",
      "sector": "Consumer Cyclical",
      "industry": "Auto Manufacturers",
      "currency": "EUR",
      "price": 89.98,
      "dividend_yield": 6.85,
      "dividend_rate": 6.36,
      "dividend_frequency": "annual",
      "payout_ratio": 47.43,
      "pe_ratio": 6.71,
      "market_cap": 45811064832,
      "market_cap_b": 45.81,
      "52w_high": 114.2,
      "52w_low": 81.68,
      "dist_from_high": 21.2,
      "max_drawdown_12m": 23.9,
      "change_6m": -9.2,
      "change_12m": -12.6,
      "beta": 0.96,
      "ex_dividend_date": "2025-05-19",
      "dividend_score": 5,
      "capital_score": 2,
      "sustainable": true,
      "price_target_avg": 116.44,
      "price_target_high": 151.0,
      "price_target_low": 92.6,
      "upside_potential": 29.4,
      "analyst_rating": "Buy",
      "analyst_count": 22,
      "scanned_at": "2026-03-06T18:26:39.616940"
    },
    {
      "ticker": "MBG.DE",
      "name": "Mercedes-Benz Group AG        N",
      "asset_type": "stock",
      "sector": "Consumer Cyclical",
      "industry": "Auto Manufacturers",
      "currency": "EUR",
      "price": 54.78,
      "dividend_yield": 6.29,
      "dividend_rate": 3.5,
      "dividend_frequency": "annual",
      "payout_ratio": 66.36,
      "pe_ratio": 8.45,
      "market_cap": 48471580672,
      "market_cap_b": 48.47,
      "52w_high": 63.17,
      "52w_low": 45.6,
      "dist_from_high": 13.3,
      "max_drawdown_12m": 25.2,
      "change_6m": 3.1,
      "change_12m": -4.5,
      "beta": 1.0,
      "ex_dividend_date": "2026-04-17",
      "dividend_score": 4,
      "capital_score": 3,
      "sustainable": true,
      "price_target_avg": 62.65,
      "price_target_high": 75.0,
      "price_target_low": 43.0,
      "upside_potential": 14.4,
      "analyst_rating": "Buy",
      "analyst_count": 24,
      "scanned_at": "2026-03-06T18:26:38.621679"
    },
    {
      "ticker": "PAH3.DE",
      "name": "Porsche Automobil Holding SE  I",
      "asset_type": "stock",
      "sector": "Consumer Cyclical",
      "industry": "Auto Manufacturers",
      "currency": "EUR",
      "price": 33.52,
      "dividend_yield": 5.6,
      "dividend_rate": 1.91,
      "dividend_frequency": "annual",
      "payout_ratio": 20.62,
      "pe_ratio": null,
      "market_cap": 10265499648,
      "market_cap_b": 10.27,
      "52w_high": 41.52,
      "52w_low": 30.46,
      "dist_from_high": 19.3,
      "max_drawdown_12m": 20.5,
      "change_6m": -6.1,
      "change_12m": -9.7,
      "beta": 0.94,
      "ex_dividend_date": "2025-06-11",
      "dividend_score": 5,
      "capital_score": 3,
      "sustainable": true,
      "price_target_avg": 39.0,
      "price_target_high": 45.0,
      "price_target_low": 31.0,
      "upside_potential": 16.3,
      "analyst_rating": "Hold",
      "analyst_count": 10,
      "scanned_at": "2026-03-06T18:26:38.976293"
    },
    {
      "ticker": "BMW.DE",
      "name": "BAYERISCHE MOTOREN WERKE AG   S",
      "asset_type": "stock",
      "sector": "Consumer Cyclical",
      "industry": "Auto Manufacturers",
      "currency": "EUR",
      "price": 79.8,
      "dividend_yield": 5.28,
      "dividend_rate": 4.3,
      "dividend_frequency": "annual",
      "payout_ratio": 37.79,
      "pe_ratio": 7.01,
      "market_cap": 48643403776,
      "market_cap_b": 48.64,
      "52w_high": 97.92,
      "52w_low": 62.96,
      "dist_from_high": 18.5,
      "max_drawdown_12m": 27.0,
      "change_6m": -9.9,
      "change_12m": -3.3,
      "beta": 0.72,
      "ex_dividend_date": "2025-05-15",
      "dividend_score": 5,
      "capital_score": 3,
      "sustainable": true,
      "price_target_avg": 92.37,
      "price_target_high": 115.0,
      "price_target_low": 69.0,
      "upside_potential": 15.8,
      "analyst_rating": "Hold",
      "analyst_count": 23,
      "scanned_at": "2026-03-06T18:26:37.259838"
    }
  ]
}