{
  "scan_date": "2026-03-05",
  "total": 48,
  "stocks": [
    {
      "ticker": "BNP.PA",
      "name": "BNP PARIBAS ACT.A",
      "sector": "Financial Services",
      "industry": "Banks - Regional",
      "currency": "EUR",
      "price": 89.32,
      "dividend_yield": 11.27,
      "dividend_rate": 9.95,
      "payout_ratio": 71.72,
      "pe_ratio": 8.68,
      "market_cap": 99751215104.0,
      "52w_high": 97.35,
      "52w_low": 61.0,
      "dividend_score": 3,
      "capital_score": 4,
      "sustainable": true,
      "ocean_accessible": false,
      "ocean_market": "eurostoxx50"
    },
    {
      "ticker": "BPE.MI",
      "name": "BPER BANCA",
      "sector": "Financial Services",
      "industry": "Banks - Regional",
      "currency": "EUR",
      "price": 11.45,
      "dividend_yield": 10.0,
      "dividend_rate": 1.1,
      "payout_ratio": 64.28,
      "pe_ratio": 10.5,
      "market_cap": 22464739328.0,
      "52w_high": 12.88,
      "52w_low": 5.31,
      "dividend_score": 4,
      "capital_score": 4,
      "sustainable": true,
      "ocean_accessible": false,
      "ocean_market": "ftse_mib"
    },
    {
      "ticker": "NTGY.MC",
      "name": "NATURGY ENERGY GROUP, S.A.",
      "sector": "Utilities",
      "industry": "Utilities - Regulated Gas",
      "currency": "EUR",
      "price": 24.84,
      "dividend_yield": 9.69,
      "dividend_rate": 2.4,
      "payout_ratio": 82.43,
      "pe_ratio": 11.39,
      "market_cap": 23011616768.0,
      "52w_high": 27.9,
      "52w_low": 23.3,
      "dividend_score": 3,
      "capital_score": 4,
      "sustainable": true,
      "ocean_accessible": false,
      "ocean_market": "ibex35"
    },
    {
      "ticker": "TEF.MC",
      "name": "TELEFONICA,S.A.",
      "sector": "Communication Services",
      "industry": "Telecom Services",
      "currency": "EUR",
      "price": 3.6,
      "dividend_yield": 8.42,
      "dividend_rate": 0.3,
      "payout_ratio": 111.11,
      "pe_ratio": null,
      "market_cap": 20332763136.0,
      "52w_high": 4.89,
      "52w_low": 3.24,
      "dividend_score": 1,
      "capital_score": 2,
      "sustainable": false,
      "ocean_accessible": false,
      "ocean_market": "eurostoxx50"
    },
    {
      "ticker": "TEP.PA",
      "name": "TELEPERFORMANCE",
      "sector": "Industrials",
      "industry": "Specialty Business Services",
      "currency": "EUR",
      "price": 56.04,
      "dividend_yield": 8.31,
      "dividend_rate": 4.5,
      "payout_ratio": 52.04,
      "pe_ratio": 6.94,
      "market_cap": 3257653760.0,
      "52w_high": 107.8,
      "52w_low": 48.08,
      "dividend_score": 5,
      "capital_score": 1,
      "sustainable": true,
      "ocean_accessible": false,
      "ocean_market": "cac40"
    },
    {
      "ticker": "ARE",
      "name": "Alexandria Real Estate Equities",
      "sector": "Real Estate",
      "industry": "REIT - Office",
      "currency": "USD",
      "price": 53.58,
      "dividend_yield": 7.81,
      "dividend_rate": 4.08,
      "payout_ratio": 689.47,
      "pe_ratio": null,
      "market_cap": 9285434368.0,
      "52w_high": 105.14,
      "52w_low": 44.1,
      "dividend_score": 1,
      "capital_score": 1,
      "sustainable": false,
      "ocean_accessible": false,
      "ocean_market": "sp500"
    },
    {
      "ticker": "NEXI.MI",
      "name": "NEXI",
      "sector": "Technology",
      "industry": "Software - Infrastructure",
      "currency": "EUR",
      "price": 3.38,
      "dividend_yield": 7.56,
      "dividend_rate": 0.25,
      "payout_ratio": 108.7,
      "pe_ratio": 14.72,
      "market_cap": 3957873152.0,
      "52w_high": 5.71,
      "52w_low": 3.05,
      "dividend_score": 1,
      "capital_score": 1,
      "sustainable": false,
      "ocean_accessible": false,
      "ocean_market": "ftse_mib"
    },
    {
      "ticker": "RNO.PA",
      "name": "RENAULT",
      "sector": "Consumer Cyclical",
      "industry": "Auto Manufacturers",
      "currency": "EUR",
      "price": 29.01,
      "dividend_yield": 7.49,
      "dividend_rate": 2.2,
      "payout_ratio": 68.01,
      "pe_ratio": null,
      "market_cap": 8408268800.0,
      "52w_high": 50.08,
      "52w_low": 28.71,
      "dividend_score": 4,
      "capital_score": 1,
      "sustainable": true,
      "ocean_accessible": false,
      "ocean_market": "cac40"
    },
    {
      "ticker": "CAG",
      "name": "ConAgra Brands, Inc.",
      "sector": "Consumer Defensive",
      "industry": "Packaged Foods",
      "currency": "USD",
      "price": 18.85,
      "dividend_yield": 7.38,
      "dividend_rate": 1.4,
      "payout_ratio": 79.1,
      "pe_ratio": null,
      "market_cap": 9017265152.0,
      "52w_high": 28.52,
      "52w_low": 15.96,
      "dividend_score": 3,
      "capital_score": 1,
      "sustainable": true,
      "ocean_accessible": false,
      "ocean_market": "sp500"
    },
    {
      "ticker": "MB.MI",
      "name": "MEDIOBANCA",
      "sector": "Financial Services",
      "industry": "Banks - Regional",
      "currency": "EUR",
      "price": 16.83,
      "dividend_yield": 7.37,
      "dividend_rate": 1.26,
      "payout_ratio": 78.42,
      "pe_ratio": 11.45,
      "market_cap": 13571712000.0,
      "52w_high": 22.34,
      "52w_low": 13.19,
      "dividend_score": 3,
      "capital_score": 3,
      "sustainable": true,
      "ocean_accessible": false,
      "ocean_market": "ftse_mib"
    },
    {
      "ticker": "ISP.MI",
      "name": "INTESA SANPAOLO",
      "sector": "Financial Services",
      "industry": "Banks - Regional",
      "currency": "EUR",
      "price": 5.42,
      "dividend_yield": 7.14,
      "dividend_rate": 0.38,
      "payout_ratio": 62.93,
      "pe_ratio": 9.51,
      "market_cap": 94268317696.0,
      "52w_high": 6.16,
      "52w_low": 3.66,
      "dividend_score": 4,
      "capital_score": 4,
      "sustainable": true,
      "ocean_accessible": false,
      "ocean_market": "eurostoxx50"
    },
    {
      "ticker": "BMED.MI",
      "name": "BANCA MEDIOLANUM",
      "sector": "Financial Services",
      "industry": "Banks - Regional",
      "currency": "EUR",
      "price": 17.64,
      "dividend_yield": 6.96,
      "dividend_rate": 1.2,
      "payout_ratio": 73.45,
      "pe_ratio": 10.56,
      "market_cap": 13040028672.0,
      "52w_high": 20.68,
      "52w_low": 11.47,
      "dividend_score": 3,
      "capital_score": 4,
      "sustainable": true,
      "ocean_accessible": false,
      "ocean_market": "ftse_mib"
    },
    {
      "ticker": "UNI.MC",
      "name": "UNICAJA BANCO, S.A.",
      "sector": "Financial Services",
      "industry": "Banks - Regional",
      "currency": "EUR",
      "price": 2.56,
      "dividend_yield": 6.94,
      "dividend_rate": 0.17,
      "payout_ratio": 56.83,
      "pe_ratio": 10.22,
      "market_cap": 6564856832.0,
      "52w_high": 3.04,
      "52w_low": 1.25,
      "dividend_score": 5,
      "capital_score": 4,
      "sustainable": true,
      "ocean_accessible": false,
      "ocean_market": "ibex35"
    },
    {
      "ticker": "ENG.MC",
      "name": "ENAGAS,S.A.",
      "sector": "Utilities",
      "industry": "Utilities - Regulated Gas",
      "currency": "EUR",
      "price": 14.57,
      "dividend_yield": 6.81,
      "dividend_rate": 1.0,
      "payout_ratio": 77.52,
      "pe_ratio": 11.3,
      "market_cap": 3788664320.0,
      "52w_high": 15.46,
      "52w_low": 12.1,
      "dividend_score": 3,
      "capital_score": 4,
      "sustainable": true,
      "ocean_accessible": false,
      "ocean_market": "ibex35"
    },
    {
      "ticker": "VOW3.DE",
      "name": "VOLKSWAGEN AG                 V",
      "sector": "Consumer Cyclical",
      "industry": "Auto Manufacturers",
      "currency": "EUR",
      "price": 94.44,
      "dividend_yield": 6.8,
      "dividend_rate": 6.36,
      "payout_ratio": 47.43,
      "pe_ratio": 7.04,
      "market_cap": 48081764352.0,
      "52w_high": 114.2,
      "52w_low": 81.68,
      "dividend_score": 5,
      "capital_score": 3,
      "sustainable": true,
      "ocean_accessible": false,
      "ocean_market": "eurostoxx50"
    },
    {
      "ticker": "SAB.MC",
      "name": "BANCO DE SABADELL",
      "sector": "Financial Services",
      "industry": "Banks - Diversified",
      "currency": "EUR",
      "price": 3.06,
      "dividend_yield": 6.78,
      "dividend_rate": 0.2,
      "payout_ratio": 105.76,
      "pe_ratio": 12.22,
      "market_cap": 15224406016.0,
      "52w_high": 3.48,
      "52w_low": 1.9,
      "dividend_score": 1,
      "capital_score": 4,
      "sustainable": false,
      "ocean_accessible": false,
      "ocean_market": "ibex35"
    },
    {
      "ticker": "KHC",
      "name": "The Kraft Heinz Company",
      "sector": "Consumer Defensive",
      "industry": "Packaged Foods",
      "currency": "USD",
      "price": 24.04,
      "dividend_yield": 6.61,
      "dividend_rate": 1.6,
      "payout_ratio": 73.06,
      "pe_ratio": null,
      "market_cap": 28457226240.0,
      "52w_high": 33.35,
      "52w_low": 21.98,
      "dividend_score": 3,
      "capital_score": 2,
      "sustainable": true,
      "ocean_accessible": false,
      "ocean_market": "sp500"
    },
    {
      "ticker": "LOG.MC",
      "name": "COMPA...IA DE DISTRIBUCION INTE",
      "sector": "Industrials",
      "industry": "Integrated Freight & Logistics",
      "currency": "EUR",
      "price": 30.96,
      "dividend_yield": 6.58,
      "dividend_rate": 2.01,
      "payout_ratio": 100.05,
      "pe_ratio": 14.81,
      "market_cap": 4090100736.0,
      "52w_high": 34.48,
      "52w_low": 26.16,
      "dividend_score": 1,
      "capital_score": 4,
      "sustainable": false,
      "ocean_accessible": false,
      "ocean_market": "ibex35"
    },
    {
      "ticker": "PFE",
      "name": "Pfizer, Inc.",
      "sector": "Healthcare",
      "industry": "Drug Manufacturers - General",
      "currency": "USD",
      "price": 26.62,
      "dividend_yield": 6.47,
      "dividend_rate": 1.72,
      "payout_ratio": 126.47,
      "pe_ratio": 19.57,
      "market_cap": 151353540608.0,
      "52w_high": 27.94,
      "52w_low": 20.92,
      "dividend_score": 1,
      "capital_score": 4,
      "sustainable": false,
      "ocean_accessible": false,
      "ocean_market": "sp500"
    },
    {
      "ticker": "HPQ",
      "name": "HP Inc.",
      "sector": "Technology",
      "industry": "Computer Hardware",
      "currency": "USD",
      "price": 19.18,
      "dividend_yield": 6.31,
      "dividend_rate": 1.2,
      "payout_ratio": 44.25,
      "pe_ratio": 7.27,
      "market_cap": 17606942720.0,
      "52w_high": 30.61,
      "52w_low": 17.56,
      "dividend_score": 5,
      "capital_score": 1,
      "sustainable": true,
      "ocean_accessible": false,
      "ocean_market": "sp500"
    },
    {
      "ticker": "MBG.DE",
      "name": "Mercedes-Benz Group AG        N",
      "sector": "Consumer Cyclical",
      "industry": "Auto Manufacturers",
      "currency": "EUR",
      "price": 56.52,
      "dividend_yield": 6.28,
      "dividend_rate": 3.5,
      "payout_ratio": 66.36,
      "pe_ratio": 8.72,
      "market_cap": 50011205632.0,
      "52w_high": 63.17,
      "52w_low": 45.6,
      "dividend_score": 4,
      "capital_score": 4,
      "sustainable": true,
      "ocean_accessible": false,
      "ocean_market": "eurostoxx50"
    },
    {
      "ticker": "RI.PA",
      "name": "PERNOD RICARD",
      "sector": "Consumer Defensive",
      "industry": "Beverages - Wineries & Distilleries",
      "currency": "EUR",
      "price": 72.64,
      "dividend_yield": 6.27,
      "dividend_rate": 4.7,
      "payout_ratio": 83.99,
      "pe_ratio": 12.97,
      "market_cap": 18291773440.0,
      "52w_high": 107.45,
      "52w_low": 71.3,
      "dividend_score": 3,
      "capital_score": 2,
      "sustainable": true,
      "ocean_accessible": false,
      "ocean_market": "cac40"
    },
    {
      "ticker": "MO",
      "name": "Altria Group, Inc.",
      "sector": "Consumer Defensive",
      "industry": "Tobacco",
      "currency": "USD",
      "price": 68.12,
      "dividend_yield": 6.15,
      "dividend_rate": 4.24,
      "payout_ratio": 100.97,
      "pe_ratio": 16.53,
      "market_cap": 114351112192.0,
      "52w_high": 70.51,
      "52w_low": 52.82,
      "dividend_score": 1,
      "capital_score": 5,
      "sustainable": false,
      "ocean_accessible": false,
      "ocean_market": "sp500"
    },
    {
      "ticker": "CPB",
      "name": "The Campbell's Company",
      "sector": "Consumer Defensive",
      "industry": "Packaged Foods",
      "currency": "USD",
      "price": 25.09,
      "dividend_yield": 5.99,
      "dividend_rate": 1.56,
      "payout_ratio": 80.41,
      "pe_ratio": 12.93,
      "market_cap": 7480187904.0,
      "52w_high": 43.85,
      "52w_low": 25.02,
      "dividend_score": 3,
      "capital_score": 1,
      "sustainable": true,
      "ocean_accessible": false,
      "ocean_market": "sp500"
    },
    {
      "ticker": "CS.PA",
      "name": "AXA",
      "sector": "Financial Services",
      "industry": "Insurance - Diversified",
      "currency": "EUR",
      "price": 38.76,
      "dividend_yield": 5.95,
      "dividend_rate": 2.32,
      "payout_ratio": 65.35,
      "pe_ratio": 11.78,
      "market_cap": 81032495104.0,
      "52w_high": 43.61,
      "52w_low": 34.0,
      "dividend_score": 4,
      "capital_score": 4,
      "sustainable": true,
      "ocean_accessible": false,
      "ocean_market": "eurostoxx50"
    },
    {
      "ticker": "UPS",
      "name": "United Parcel Service, Inc.",
      "sector": "Industrials",
      "industry": "Integrated Freight & Logistics",
      "currency": "USD",
      "price": 110.5,
      "dividend_yield": 5.79,
      "dividend_rate": 6.56,
      "payout_ratio": 100.0,
      "pe_ratio": 16.84,
      "market_cap": 93825736704.0,
      "52w_high": 123.7,
      "52w_low": 82.0,
      "dividend_score": 2,
      "capital_score": 2,
      "sustainable": true,
      "ocean_accessible": false,
      "ocean_market": "sp500"
    },
    {
      "ticker": "COL.MC",
      "name": "COLONIAL SFL, SOCIMI. S.A.",
      "sector": "Real Estate",
      "industry": "REIT - Office",
      "currency": "EUR",
      "price": 5.33,
      "dividend_yield": 5.71,
      "dividend_rate": 0.3,
      "payout_ratio": 41.49,
      "pe_ratio": 7.4,
      "market_cap": 3267752192.0,
      "52w_high": 6.34,
      "52w_low": 4.98,
      "dividend_score": 5,
      "capital_score": 3,
      "sustainable": true,
      "ocean_accessible": false,
      "ocean_market": "ibex35"
    },
    {
      "ticker": "PST.MI",
      "name": "POSTE ITALIANE",
      "sector": "Industrials",
      "industry": "Conglomerates",
      "currency": "EUR",
      "price": 22.27,
      "dividend_yield": 5.71,
      "dividend_rate": 1.25,
      "payout_ratio": 64.48,
      "pe_ratio": 13.34,
      "market_cap": 28819959808.0,
      "52w_high": 23.87,
      "52w_low": 14.52,
      "dividend_score": 4,
      "capital_score": 5,
      "sustainable": true,
      "ocean_accessible": false,
      "ocean_market": "ftse_mib"
    },
    {
      "ticker": "DOW",
      "name": "Dow Inc.",
      "sector": "Basic Materials",
      "industry": "Chemicals",
      "currency": "USD",
      "price": 32.34,
      "dividend_yield": 5.69,
      "dividend_rate": 1.75,
      "payout_ratio": 700.0,
      "pe_ratio": null,
      "market_cap": 23205052416.0,
      "52w_high": 38.36,
      "52w_low": 20.4,
      "dividend_score": 1,
      "capital_score": 2,
      "sustainable": false,
      "ocean_accessible": false,
      "ocean_market": "sp500"
    },
    {
      "ticker": "PAH3.DE",
      "name": "Porsche Automobil Holding SE  I",
      "sector": "Consumer Cyclical",
      "industry": "Auto Manufacturers",
      "currency": "EUR",
      "price": 34.2,
      "dividend_yield": 5.64,
      "dividend_rate": 1.91,
      "payout_ratio": 20.62,
      "pe_ratio": null,
      "market_cap": 10473749504.0,
      "52w_high": 41.52,
      "52w_low": 30.46,
      "dividend_score": 5,
      "capital_score": 3,
      "sustainable": true,
      "ocean_accessible": false,
      "ocean_market": "dax40"
    },
    {
      "ticker": "VIS.MC",
      "name": "VISCOFAN, S.A.",
      "sector": "Consumer Cyclical",
      "industry": "Packaging & Containers",
      "currency": "EUR",
      "price": 59.6,
      "dividend_yield": 5.6,
      "dividend_rate": 3.17,
      "payout_ratio": 89.73,
      "pe_ratio": 17.13,
      "market_cap": 2729076992.0,
      "52w_high": 68.7,
      "52w_low": 48.35,
      "dividend_score": 2,
      "capital_score": 3,
      "sustainable": true,
      "ocean_accessible": false,
      "ocean_market": "ibex35"
    },
    {
      "ticker": "BGN.MI",
      "name": "BANCA GENERALI",
      "sector": "Financial Services",
      "industry": "Banks - Regional",
      "currency": "EUR",
      "price": 53.2,
      "dividend_yield": 5.6,
      "dividend_rate": 2.9,
      "payout_ratio": 70.27,
      "pe_ratio": 13.57,
      "market_cap": 6059965952.0,
      "52w_high": 59.45,
      "52w_low": 41.7,
      "dividend_score": 3,
      "capital_score": 4,
      "sustainable": true,
      "ocean_accessible": false,
      "ocean_market": "ftse_mib"
    },
    {
      "ticker": "VZ",
      "name": "Verizon Communications Inc.",
      "sector": "Communication Services",
      "industry": "Telecom Services",
      "currency": "USD",
      "price": 51.2,
      "dividend_yield": 5.56,
      "dividend_rate": 2.83,
      "payout_ratio": 50.37,
      "pe_ratio": 12.61,
      "market_cap": 215945428992.0,
      "52w_high": 51.41,
      "52w_low": 38.39,
      "dividend_score": 4,
      "capital_score": 5,
      "sustainable": true,
      "ocean_accessible": false,
      "ocean_market": "sp500"
    },
    {
      "ticker": "PRU",
      "name": "Prudential Financial, Inc.",
      "sector": "Financial Services",
      "industry": "Insurance - Life",
      "currency": "USD",
      "price": 98.79,
      "dividend_yield": 5.52,
      "dividend_rate": 5.45,
      "payout_ratio": 54.05,
      "pe_ratio": 9.89,
      "market_cap": 34378919936.0,
      "52w_high": 119.76,
      "52w_low": 90.38,
      "dividend_score": 4,
      "capital_score": 3,
      "sustainable": true,
      "ocean_accessible": false,
      "ocean_market": "sp500"
    },
    {
      "ticker": "GIS",
      "name": "General Mills, Inc.",
      "sector": "Consumer Defensive",
      "industry": "Packaged Foods",
      "currency": "USD",
      "price": 43.56,
      "dividend_yield": 5.48,
      "dividend_rate": 2.44,
      "payout_ratio": 52.04,
      "pe_ratio": 9.37,
      "market_cap": 23242835968.0,
      "52w_high": 67.35,
      "52w_low": 42.79,
      "dividend_score": 4,
      "capital_score": 1,
      "sustainable": true,
      "ocean_accessible": false,
      "ocean_market": "sp500"
    },
    {
      "ticker": "BKT.MC",
      "name": "BANKINTER, S.A.",
      "sector": "Financial Services",
      "industry": "Banks - Regional",
      "currency": "EUR",
      "price": 13.54,
      "dividend_yield": 5.42,
      "dividend_rate": 0.73,
      "payout_ratio": 49.14,
      "pe_ratio": 11.57,
      "market_cap": 12168347648.0,
      "52w_high": 14.99,
      "52w_low": 7.7,
      "dividend_score": 5,
      "capital_score": 4,
      "sustainable": true,
      "ocean_accessible": false,
      "ocean_market": "ibex35"
    },
    {
      "ticker": "RED.MC",
      "name": "REDEIA CORPORACION, S.A.",
      "sector": "Utilities",
      "industry": "Utilities - Regulated Electric",
      "currency": "EUR",
      "price": 14.82,
      "dividend_yield": 5.39,
      "dividend_rate": 0.8,
      "payout_ratio": 85.47,
      "pe_ratio": 15.77,
      "market_cap": 8008847360.0,
      "52w_high": 19.51,
      "52w_low": 14.15,
      "dividend_score": 2,
      "capital_score": 3,
      "sustainable": true,
      "ocean_accessible": false,
      "ocean_market": "ibex35"
    },
    {
      "ticker": "REP.MC",
      "name": "REPSOL,  S.A.",
      "sector": "Energy",
      "industry": "Oil & Gas Integrated",
      "currency": "EUR",
      "price": 20.11,
      "dividend_yield": 5.32,
      "dividend_rate": 1.1,
      "payout_ratio": 60.19,
      "pe_ratio": 12.41,
      "market_cap": 22304151552.0,
      "52w_high": 20.82,
      "52w_low": 9.41,
      "dividend_score": 4,
      "capital_score": 5,
      "sustainable": true,
      "ocean_accessible": false,
      "ocean_market": "ibex35"
    },
    {
      "ticker": "AZM.MI",
      "name": "AZIMUT",
      "sector": "Financial Services",
      "industry": "Asset Management",
      "currency": "EUR",
      "price": 33.8,
      "dividend_yield": 5.27,
      "dividend_rate": 1.75,
      "payout_ratio": 48.1,
      "pe_ratio": 9.29,
      "market_cap": 4804690432.0,
      "52w_high": 37.32,
      "52w_low": 19.29,
      "dividend_score": 5,
      "capital_score": 4,
      "sustainable": true,
      "ocean_accessible": false,
      "ocean_market": "ftse_mib"
    },
    {
      "ticker": "SPM.MI",
      "name": "SAIPEM",
      "sector": "Energy",
      "industry": "Oil & Gas Equipment & Services",
      "currency": "EUR",
      "price": 3.35,
      "dividend_yield": 5.22,
      "dividend_rate": 0.17,
      "payout_ratio": 106.4,
      "pe_ratio": 20.94,
      "market_cap": 6499947008.0,
      "52w_high": 3.69,
      "52w_low": 1.59,
      "dividend_score": 1,
      "capital_score": 3,
      "sustainable": false,
      "ocean_accessible": false,
      "ocean_market": "ftse_mib"
    },
    {
      "ticker": "BMW.DE",
      "name": "BAYERISCHE MOTOREN WERKE AG   S",
      "sector": "Consumer Cyclical",
      "industry": "Auto Manufacturers",
      "currency": "EUR",
      "price": 82.64,
      "dividend_yield": 5.21,
      "dividend_rate": 4.3,
      "payout_ratio": 37.79,
      "pe_ratio": 7.26,
      "market_cap": 50374574080.0,
      "52w_high": 97.92,
      "52w_low": 62.96,
      "dividend_score": 5,
      "capital_score": 3,
      "sustainable": true,
      "ocean_accessible": false,
      "ocean_market": "eurostoxx50"
    },
    {
      "ticker": "ENI.MI",
      "name": "ENI",
      "sector": "Energy",
      "industry": "Oil & Gas Integrated",
      "currency": "EUR",
      "price": 19.96,
      "dividend_yield": 5.19,
      "dividend_rate": 1.04,
      "payout_ratio": 123.17,
      "pe_ratio": 24.34,
      "market_cap": 58729177088.0,
      "52w_high": 20.77,
      "52w_low": 11.01,
      "dividend_score": 1,
      "capital_score": 5,
      "sustainable": false,
      "ocean_accessible": false,
      "ocean_market": "eurostoxx50"
    },
    {
      "ticker": "ENEL.MI",
      "name": "ENEL",
      "sector": "Utilities",
      "industry": "Utilities - Diversified",
      "currency": "EUR",
      "price": 9.57,
      "dividend_yield": 5.12,
      "dividend_rate": 0.49,
      "payout_ratio": 78.33,
      "pe_ratio": 15.95,
      "market_cap": 95976357888.0,
      "52w_high": 10.31,
      "52w_low": 6.52,
      "dividend_score": 3,
      "capital_score": 4,
      "sustainable": true,
      "ocean_accessible": false,
      "ocean_market": "eurostoxx50"
    },
    {
      "ticker": "ACX.MC",
      "name": "ACERINOX, S.A.",
      "sector": "Basic Materials",
      "industry": "Steel",
      "currency": "EUR",
      "price": 12.81,
      "dividend_yield": 5.1,
      "dividend_rate": 0.62,
      "payout_ratio": 221.43,
      "pe_ratio": 45.75,
      "market_cap": 3192809728.0,
      "52w_high": 14.1,
      "52w_low": 8.3,
      "dividend_score": 1,
      "capital_score": 3,
      "sustainable": false,
      "ocean_accessible": false,
      "ocean_market": "ibex35"
    },
    {
      "ticker": "BBVA.MC",
      "name": "BANCO BILBAO VIZCAYA ARGENTARIA",
      "sector": "Financial Services",
      "industry": "Banks - Diversified",
      "currency": "EUR",
      "price": 18.84,
      "dividend_yield": 5.09,
      "dividend_rate": 0.92,
      "payout_ratio": 41.48,
      "pe_ratio": 10.7,
      "market_cap": 107151228928.0,
      "52w_high": 22.33,
      "52w_low": 10.11,
      "dividend_score": 5,
      "capital_score": 4,
      "sustainable": true,
      "ocean_accessible": false,
      "ocean_market": "eurostoxx50"
    },
    {
      "ticker": "BXP",
      "name": "BXP, Inc.",
      "sector": "Real Estate",
      "industry": "REIT - Office",
      "currency": "USD",
      "price": 56.36,
      "dividend_yield": 5.07,
      "dividend_rate": 2.8,
      "payout_ratio": 193.1,
      "pe_ratio": 32.39,
      "market_cap": 9974376448.0,
      "52w_high": 79.33,
      "52w_low": 53.36,
      "dividend_score": 1,
      "capital_score": 1,
      "sustainable": false,
      "ocean_accessible": false,
      "ocean_market": "sp500"
    },
    {
      "ticker": "CABK.MC",
      "name": "CAIXABANK, S.A.",
      "sector": "Financial Services",
      "industry": "Banks - Regional",
      "currency": "EUR",
      "price": 10.13,
      "dividend_yield": 5.01,
      "dividend_rate": 0.5,
      "payout_ratio": 57.16,
      "pe_ratio": 12.82,
      "market_cap": 70876536832.0,
      "52w_high": 11.57,
      "52w_low": 5.49,
      "dividend_score": 4,
      "capital_score": 4,
      "sustainable": true,
      "ocean_accessible": false,
      "ocean_market": "ibex35"
    },
    {
      "ticker": "ENGI.PA",
      "name": "ENGIE",
      "sector": "Utilities",
      "industry": "Utilities - Diversified",
      "currency": "EUR",
      "price": 27.26,
      "dividend_yield": 5.0,
      "dividend_rate": 1.35,
      "payout_ratio": 72.91,
      "pe_ratio": 13.43,
      "market_cap": 66234658816.0,
      "52w_high": 29.89,
      "52w_low": 16.66,
      "dividend_score": 3,
      "capital_score": 5,
      "sustainable": true,
      "ocean_accessible": false,
      "ocean_market": "eurostoxx50"
    }
  ]
}